fetch_med/__init__.py
fetch_med/main.py
fetch_med/pubmed.py
fetch_med-0.0.2.dist-info/entry_points.txt
fetch_med-0.0.2.dist-info/METADATA
fetch_med-0.0.2.dist-info/WHEEL
fetch_med-0.0.2.dist-info/RECORD
