Metadata-Version: 2.3
Name: fetch-med
Version: 0.0.2
Summary: A tool to fetch research papers
Author: pallavdata
Requires-Python: >=3.8,<4.0
Classifier: Programming Language :: Python :: 3
Classifier: Programming Language :: Python :: 3.8
Classifier: Programming Language :: Python :: 3.9
Classifier: Programming Language :: Python :: 3.10
Classifier: Programming Language :: Python :: 3.11
Classifier: Programming Language :: Python :: 3.12
Classifier: Programming Language :: Python :: 3.13
Requires-Dist: beautifulsoup4 (>=4.13.3)
Requires-Dist: deep-translator (>=1.11.4)
Requires-Dist: lxml (>=5.3.1)
Requires-Dist: openpyxl (>=3.1.5)
Requires-Dist: pandas (>=2.0.3)
Requires-Dist: requests (>=2.32.3)
